Metadata-Version: 2.1
Name: sceptre-aws-stackoutput-resolver
Version: 1.0.0
Summary: Sceptre AWS StackOuput Resolver
Home-page: https://github.com/sceptre/sceptre-aws-stackoutput-resolver
Author: Sceptre
Author-email: sceptre@cloudreach.com
License: Apache2
Keywords: sceptre,sceptre-resolver
Platform: UNKNOWN
Classifier: Intended Audience :: Developers
Classifier: Natural Language :: English
Classifier: Environment :: Console
Classifier: Programming Language :: Python :: 2.7
Classifier: Programming Language :: Python :: 3.5
Classifier: Programming Language :: Python :: 3.6
Classifier: Programming Language :: Python :: 3.7
Requires-Dist: packaging (==16.8)
Provides-Extra: test
Requires-Dist: pytest (>=3.2) ; extra == 'test'
